MANIFEST.in
README.md
build.txt
requirements.txt
setup.py
snot.py
slickqa_snot.egg-info/PKG-INFO
slickqa_snot.egg-info/SOURCES.txt
slickqa_snot.egg-info/dependency_links.txt
slickqa_snot.egg-info/entry_points.txt
slickqa_snot.egg-info/requires.txt
slickqa_snot.egg-info/top_level.txt