Metadata-Version: 1.0
Name: slickqa-snot
Version: 1.0.2960
Summary: A plugin to nose to allow results from python tests to be put into slick.
Home-page: http://github.com/slickqa/snot
Author: Slick Developers
Author-email: UNKNOWN
License: License :: OSI Approved :: Apache Software License
Platform: UNKNOWN
